{
    "uuids": {
        "phone_id": "2f438e31-9f95-4e9c-ac88-f1f77f9b8fcd",
        "uuid": "609ec95e-3652-456e-af39-a7870a6f5530",
        "client_session_id": "bc3b4be2-1437-4c82-823e-5929e0c1ec64",
        "advertising_id": "001e1bcb-5968-4991-84be-4808814e681f",
        "android_device_id": "android-4d74c46f6beab02f",
        "request_id": "f1ce65d2-daac-4fa1-a85f-065d170984b7",
        "tray_session_id": "557b5aea-4434-480b-b2b3-27456038b092"
    },
    "mid": "aB9qFQABAAGAeQ2Vo_47C4n2kfrB",
    "ig_u_rur": null,
    "ig_www_claim": null,
    "authorization_data": {
        "ds_user_id": "74113551733",
        "sessionid": "74113551733%3AweVf75ZqdVMgoQ%3A0%3AAYcs_X_pTJVllzDDhMnbN0HONZO9M9PJ1O_wocnS2w"
    },
    "cookies": {},
    "last_login": 1746889278.8164165,
    "device_settings": {
        "app_version": "269.0.0.18.75",
        "android_version": 26,
        "android_release": "8.0.0",
        "dpi": "480dpi",
        "resolution": "1080x1920",
        "manufacturer": "OnePlus",
        "device": "devitron",
        "model": "6T Dev",
        "cpu": "qcom",
        "version_code": "314665256"
    },
    "user_agent": "Instagram 269.0.0.18.75 Android (26/8.0.0; 480dpi; 1080x1920; OnePlus; 6T Dev; devitron; qcom; en_US; 314665256)",
    "country": "US",
    "country_code": 1,
    "locale": "en_US",
    "timezone_offset": -14400
}